{"namedChunkGroups":{"polyfill":{"name":"polyfill","assets":[{"name":"webpack-runtime-a7e703d2cf1425b61a6f.js","size":4294},{"name":"polyfill-a86210d5e61ece1b4f68.js","size":82631}],"filteredAssets":0,"assetsSize":86925,"filteredAuxiliaryAssets":2,"auxiliaryAssetsSize":218936},"app":{"name":"app","assets":[{"name":"webpack-runtime-a7e703d2cf1425b61a6f.js","size":4294},{"name":"styles.33774eb8a95979a6a913.css","size":41060},{"name":"framework-12faecb6c7b91576bc1d.js","size":127685},{"name":"app-a84af6ce717b876a4717.js","size":50585}],"filteredAssets":0,"assetsSize":223624,"filteredAuxiliaryAssets":7,"auxiliaryAssetsSize":637179},"component---src-pages-index-js":{"name":"component---src-pages-index-js","assets":[{"name":"styles.33774eb8a95979a6a913.css","size":41060},{"name":"component---src-pages-index-js-199f85ec0ac56993944c.js","size":11580}],"filteredAssets":0,"assetsSize":52640,"filteredAuxiliaryAssets":5,"auxiliaryAssetsSize":139623}},"assetsByChunkName":{"polyfill":["webpack-runtime-a7e703d2cf1425b61a6f.js","polyfill-a86210d5e61ece1b4f68.js"],"app":["webpack-runtime-a7e703d2cf1425b61a6f.js","styles.33774eb8a95979a6a913.css","framework-12faecb6c7b91576bc1d.js","app-a84af6ce717b876a4717.js"],"component---src-pages-index-js":["styles.33774eb8a95979a6a913.css","component---src-pages-index-js-199f85ec0ac56993944c.js"]},"childAssetsByChunkName":{}}